HW2/adder.t.v
// Adder testbench
`timescale 1 ns / 1 ps
`include "adder.v"

module testFullAdder();
    reg a, b, carryin;
    wire sum, carryout;

    structuralFullAdder adder (sum, carryout, a, b, carryin);

    initial begin
        // Your test code here
    $dumpfile("adder.vcd");
    $dumpvars();

    $display("Cin A B | Sum Cout | Expec Sum | Expec Cout");
    a=0;b=0;carryin=0; #1000 
    $display("%b   %b %b | %b    %b   | 0         | 0", carryin, a, b, sum, carryout);
    a=0;b=0;carryin=1; #1000 
    $display("%b   %b %b | %b    %b   | 1         | 0", carryin, a, b, sum, carryout);
    a=0;b=1;carryin=0; #1000 
    $display("%b   %b %b | %b    %b   | 1         | 0", carryin, a, b, sum, carryout);
    a=0;b=1;carryin=1; #1000 
    $display("%b   %b %b | %b    %b   | 0         | 1", carryin, a, b, sum, carryout);
    a=1;b=0;carryin=0; #1000 
    $display("%b   %b %b | %b    %b   | 1         | 0", carryin, a, b, sum, carryout);
    a=1;b=0;carryin=1; #1000 
    $display("%b   %b %b | %b    %b   | 0         | 1", carryin, a, b, sum, carryout);
    a=1;b=1;carryin=0; #1000 
    $display("%b   %b %b | %b    %b   | 0         | 1", carryin, a, b, sum, carryout);
    a=1;b=1;carryin=1; #1000 
    $display("%b   %b %b | %b    %b   | 1         | 1", carryin, a, b, sum, carryout);
    $finish(); 
    end
endmodule

HW2/adder.v
// Adder circuit
`define AND and #50
`define XOR xor #50
`define OR or #50
module behavioralFullAdder
(
    output sum, 
    output carryout,
    input a, 
    input b, 
    input carryin
);
    // Uses concatenation operator and built-in '+'
    assign {carryout, sum}=a+b+carryin;
endmodule

module structuralFullAdder
(
    output sum, 
    output carryout,
    input a, 
    input b, 
    input carryin
);
    // Your adder code here
   wire abXOR;
   wire abAND;
   wire cAND;
   
   `XOR inputXOR(abXOR, a, b);
   `AND inputAND(abAND, a, b);
   `AND carryAND(cAND, abXOR, carryin);
   `XOR outXOR(sum, abXOR, carryin);
   `OR carryOR(carryout, cAND, abAND);
endmodule

HW2/adder.vcd
$date
	Thu Sep 20 22:57:57 2018
$end
$version
	Icarus Verilog
$end
$timescale
	1ps
$end
$scope module behavioralFullAdder $end
$var wire 1 ! a $end
$var wire 1 " b $end
$var wire 1 # carryin $end
$var wire 1 $ sum $end
$var wire 1 % carryout $end
$upscope $end
$scope module testFullAdder $end
$var wire 1 & sum $end
$var wire 1 ' carryout $end
$var reg 1 ( a $end
$var reg 1 ) b $end
$var reg 1 * carryin $end
$scope module adder $end
$var wire 1 ( a $end
$var wire 1 + abAND $end
$var wire 1 , abXOR $end
$var wire 1 ) b $end
$var wire 1 - cAND $end
$var wire 1 * carryin $end
$var wire 1 ' carryout $end
$var wire 1 & sum $end
$upscope $end
$upscope $end
$enddefinitions $end
#0
$dumpvars
x-
x,
x+
0*
0)
0(
x'
x&
x%
x$
z#
z"
z!
$end
#50000
0-
0+
0,
#100000
0'
0&
#1000000
1*
#1050000
1&
#2000000
0*
1)
#2050000
0&
1,
#2100000
1&
#3000000
1*
#3050000
1-
0&
#3100000
1'
#4000000
0*
0)
1(
#4050000
0-
1&
#4100000
0'
#5000000
1*
#5050000
1-
0&
#5100000
1'
#6000000
0*
1)
#6050000
0-
1&
0,
1+
#6100000
0&
#7000000
1*
#7050000
1&
